devbricksx/__init__.py
devbricksx/apm/__init__.py
devbricksx/apm/exec_time.py
devbricksx/async/__init__.py
devbricksx/async/managed_thread.py
devbricksx/common/__init__.py
devbricksx/common/json_convert.py
devbricksx/common/parser.py
devbricksx/common/quality_ops.py
devbricksx/common/string_ops.py
devbricksx/development/__init__.py
devbricksx/development/log.py
devbricksx/image/__init__.py
devbricksx/image/image_utils.py
devbricksx/text/__init__.py
devbricksx/text/text_utils.py
devbricksx-0.1.7.dist-info/licenses/LICENSE
devbricksx-0.1.7.dist-info/METADATA
devbricksx-0.1.7.dist-info/WHEEL
devbricksx-0.1.7.dist-info/top_level.txt
devbricksx-0.1.7.dist-info/RECORD
