Metadata-Version: 2.4
Name: devbricksx
Version: 0.1.7
Summary: DevBricks X Python provides several classes which will usually be used in everyday Python development
Home-page: https://github.com/dailystudio/devbricksx-py
Author: Daily Studio
Author-email: dailystudio2010@gmail.com
License: Apache License 2.0
Classifier: Programming Language :: Python :: 3
Classifier: License :: OSI Approved :: Apache Software License
Classifier: Operating System :: OS Independent
Requires-Python: >=3.6
License-File: LICENSE
Requires-Dist: Pillow>=10.2.0
Requires-Dist: numpy
Requires-Dist: jsons
Requires-Dist: filetype
Requires-Dist: typish
Dynamic: author
Dynamic: author-email
Dynamic: classifier
Dynamic: description
Dynamic: description-content-type
Dynamic: home-page
Dynamic: license
Dynamic: license-file
Dynamic: requires-dist
Dynamic: requires-python
Dynamic: summary
